fastfd/__init__.py
fastfd/_axis.py
fastfd/_discretizedscalar.py
fastfd/_fdmodel.py
fastfd/_modelmatrix.py
fastfd/_scalar.py
fastfd/_utils.py
FastFD-0.1.dist-info/LICENSE
FastFD-0.1.dist-info/METADATA
FastFD-0.1.dist-info/WHEEL
FastFD-0.1.dist-info/top_level.txt
FastFD-0.1.dist-info/RECORD
