Metadata-Version: 2.1
Name: FastFD
Version: 0.1
Summary: A finite difference simulation library
Home-page: https://github.com/stefanmeili/fastfd
Author: Stefan Meili
Author-email: stefan.meili@gmail.com
License: UNKNOWN
Project-URL: Bug Tracker, https://github.com/stefanmeili/fastfd/issues
Platform: UNKNOWN
Classifier: Programming Language :: Python :: 3
Classifier: Programming Language :: Python :: 3.6
Classifier: License :: OSI Approved :: MIT License
Classifier: Operating System :: OS Independent
Requires-Python: >= 3.6
Requires-Dist: numpy
Requires-Dist: scipy
